flame_utils/__init__.py
flame_utils/data_manipulation.py
flame_utils/data_operation.py
flame_utils/kernels.py
flame_utils/misc.py
flame_utils_a-1.0.0.dist-info/LICENSE.txt
flame_utils_a-1.0.0.dist-info/METADATA
flame_utils_a-1.0.0.dist-info/WHEEL
flame_utils_a-1.0.0.dist-info/top_level.txt
flame_utils_a-1.0.0.dist-info/RECORD
